<?xml version="1.0" encoding="utf-8"?>
<!DOCTYPE hibernate-mapping PUBLIC "-//Hibernate/Hibernate Mapping DTD 3.0//EN"
"http://hibernate.sourceforge.net/hibernate-mapping-3.0.dtd">
<!-- 
    Mapping file autogenerated by MyEclipse Persistence Tools
-->
<hibernate-mapping>
    <class name="com.winchannel.order.model.OrderSap" table="ORDER_SAP">
        <id name="id" type="java.lang.Long">
            <column name="ID" precision="10" scale="0" />
            <generator class="identity" />
        </id>
        <property name="orderCode" type="java.lang.String">
            <column name="ORDER_CODE" length="32" not-null="true" />
        </property>
        <property name="orderDate" type="java.util.Date">
            <column name="ORDER_DATE" length="23" />
        </property>
        <property name="custWillCode" type="java.lang.String">
            <column name="CUST_WILL_CODE" length="64" />
        </property>
        <property name="custName" type="java.lang.String">
            <column name="CUST_NAME" length="128" />
        </property>
        <property name="custCode" type="java.lang.String">
            <column name="CUST_CODE" length="32" />
        </property>
        <property name="dateFreeze" type="java.lang.String">
            <column name="DATE_FREEZE" length="32" />
        </property>
        <property name="quotaFreeze" type="java.lang.String">
            <column name="QUOTA_FREEZE" length="32" />
        </property>
        <property name="priceFreeze" type="java.lang.String">
            <column name="PRICE_FREEZE" length="32" />
        </property>
        <property name="childClass" type="java.lang.String">
            <column name="CHILD_CLASS" length="32" />
        </property>
        <property name="skuName" type="java.lang.String">
            <column name="SKU_NAME" length="128" />
        </property>
        <property name="skuCode" type="java.lang.String">
            <column name="SKU_CODE" length="64" />
        </property>
        <property name="orderQua" type="java.lang.Double">
            <column name="ORDER_QUA" precision="15" scale="4" />
        </property>
        <property name="stockQua" type="java.lang.Double">
            <column name="STOCK_QUA" precision="15" scale="4" />
        </property>
        <property name="stockName" type="java.lang.String">
            <column name="STOCK_NAME" length="128" />
        </property>
        <property name="stockNoQua" type="java.lang.Double">
            <column name="STOCK_NO_QUA" precision="15" scale="4" />
        </property>
        <property name="planGoodsQua" type="java.lang.Double">
            <column name="PLAN_GOODS_QUA" precision="15" scale="4" />
        </property>
        <property name="noGoodsQua" type="java.lang.Double">
            <column name="NO_GOODS_QUA" precision="15" scale="4" />
        </property>
        <property name="factGoodsQua" type="java.lang.Double">
            <column name="FACT_GOODS_QUA" precision="15" scale="4" />
        </property>
        <property name="noAccountQua" type="java.lang.Double">
            <column name="NO_ACCOUNT_QUA" precision="15" scale="4" />
        </property>
        <property name="closeQua" type="java.lang.Double">
            <column name="CLOSE_QUA" precision="15" scale="4" />
        </property>
        <property name="sysBillQua" type="java.lang.Double">
            <column name="SYS_BILL_QUA" precision="15" scale="4" />
        </property>
        <property name="price" type="java.lang.Double">
            <column name="PRICE" precision="15" scale="4" />
        </property>
        <property name="innnerOrderCode" type="java.lang.String">
            <column name="INNNER_ORDER_CODE" length="64" />
        </property>
        <property name="saleOrg" type="java.lang.String">
            <column name="SALE_ORG" length="64" />
        </property>
        <property name="province" type="java.lang.String">
            <column name="PROVINCE" length="64" />
        </property>
        <property name="status" type="java.lang.Integer">
            <column name="STATUS" not-null="true" />
        </property>
        <property name="createdDate" type="java.util.Date">
            <column name="CREATED_DATE" length="23" not-null="true" />
        </property>
        <property name="createdByid" type="java.lang.Long">
            <column name="CREATED_BYID" precision="10" scale="0" not-null="true" />
        </property>
        <property name="createdByname" type="java.lang.String">
            <column name="CREATED_BYNAME" length="50" not-null="true" />
        </property>
        <property name="updatedDate" type="java.util.Date">
            <column name="UPDATED_DATE" length="23" />
        </property>
        <property name="updatedByid" type="java.lang.Long">
            <column name="UPDATED_BYID" precision="10" scale="0" />
        </property>
        <property name="updatedByname" type="java.lang.String">
            <column name="UPDATED_BYNAME" length="50" />
        </property>
        <property name="sapOrderQua" type="java.lang.Double">
            <column name="SAP_ORDER_QUA" precision="15" scale="4" />
        </property>
        <property name="confirmQua" type="java.lang.Double">
            <column name="CONFIRM_QUA" precision="15" scale="4" />
        </property>
        <property name="noConfirmQua" type="java.lang.Double">
            <column name="NO_CONFIRM_QUA" precision="15" scale="4" />
        </property>
        <property name="refuseMemo" type="java.lang.String">
            <column name="REFUSE_MEMO" length="64" />
        </property>
        <property name="useMemo" type="java.lang.String">
            <column name="USE_MEMO" length="64" />
        </property>
        
        <property name="prodBigClass" type="java.lang.String">
            <column name="PROD_BIG_CLASS" length="128" />
        </property>
        <property name="factoryName" type="java.lang.String">
            <column name="FACTORY_NAME" length="128" />
        </property>
        
       <property name="khyqsl" type="java.lang.Double">
            <column name="KHYQSL" precision="15" scale="4" />
        </property>
        <property name="xydjsl" type="java.lang.Double">
            <column name="XYDJSL" precision="15" scale="4" />
        </property>
        <property name="jgdjsl" type="java.lang.Double">
            <column name="JGDJSL" precision="15" scale="4" />
        </property>
        <property name="nfkimgC" type="java.lang.Double">
            <column name="NFKIMG_C" precision="15" scale="4" />
        </property>
        <property name="dataDownLoadDate" type="java.util.Date">
            <column name="data_download_date" length="23" />
        </property> 
    </class>
</hibernate-mapping>
